rtl/lib/tristate_buff_n/tristate_buff_n.v
`timescale 1ns/1ps

module tristate_buff_n #(parameter WIDTH = 1) (input en, input [WIDTH-1:0] a, output [WIDTH-1:0] y);
assign y = en ? a :{WIDTH{1'bz}};
endmodule

rtl/lib/full_adder/full_adder.v
`timescale 1ns/1ps

module full_adder (input a, b, cin, output reg sum, cout);
reg p, g;

always @ (*) begin 
 p = a ^ b;
 g  = a & b;
 sum = p ^ cin;
 cout  = g | (p & cin);
end

endmodule

rtl/lib/en_dff/en_dff.v
module en_dff #(parameter WIDTH = 1) (input en, input clk, input reset, input [WIDTH-1:0] d, output reg q);

always @ (posedge clk, posedge reset) 
  if (en) begin 
   q <= d;
  end else if (reset) begin 
    q <= 0;
  end
  
endmodule

rtl/submodules/alu/alu.v
module alu #(parameter WIDTH = 8) (input [WIDTH-1:0] a, b, input clk, input reset_sig, input en_a, input en_b, input en_res, input a_out, input add_sub, output [WIDTH-1:0] result, output reg carry_flag, output [WIDTH-1:0] a_result, output reg zero_flag);

wire [WIDTH-1:0] intern_a, xor_intern_b, intern_b;
wire [WIDTH-1:0] internal_sum;
wire [WIDTH:0] carry;
assign carry[0] = add_sub;

genvar i;
generate 
  for (i = 0; i < WIDTH; i = i +1) begin: en_flip_flop
     // Register A
      en_dff #(.WIDTH(1)) a_input (.clk(clk), .en(en_a), .reset(reset_sig), .d(a[i]), .q(intern_a[i]));

      tristate_buff_n #(.WIDTH(1)) a_output (.en(a_out), .a(intern_a[i]), .y(a_result[i])); // Use a tri-state buffer to control when the value of a (intern_a) is output to a_result. The buffer will only drive a_result when a_out is high, allowing for better control over when the value of a is visible to other parts of the system.

     // Register B
      en_dff #(.WIDTH(1)) b_input (.clk(clk), .en(en_b), .reset(reset_sig), .d(b[i]), .q(xor_intern_b[i]));

        assign intern_b[i] = xor_intern_b[i] ^ add_sub; // XOR the registered value of b (xor_intern_b) with the add_sub signal to determine whether we are performing addition or subtraction. If add_sub is 0, intern_b will be the same as xor_intern_b (which is the registered value of b). If add_sub is 1, intern_b will be the bitwise complement of xor_intern_b, which is necessary for performing subtraction using two's complement representation.

      // Full Adder
      full_adder fa (.a(intern_a[i]), .b(intern_b[i]), .cin(carry[i]), .sum(internal_sum[i]), .cout(carry[i + 1]));

      tristate_buff_n #(.WIDTH(1)) res_output (.en(en_res), .a(internal_sum[i]), .y(result[i])); // Use a tri-state buffer to control when the result of the addition or subtraction is output to the result bus. The buffer will only drive the result bus when en_res is high, allowing for better control over when the ALU's output is visible to other parts of the system.
   end
endgenerate

always @ (*) begin 

   zero_flag = ~(|internal_sum); // The zero_flag is set to 1 if all bits of the sum are 0, indicating that the result of the addition or subtraction is zero. This can be useful for conditional operations or for signaling certain conditions in a larger system.

   carry_flag = carry[WIDTH]; // Output the final carry-out from the most significant bit of the addition or subtraction operation. This indicates whether there was an overflow in the case of addition or a borrow in the case of subtraction, which can be important for certain applications or for further processing in a larger system.

end
 endmodule

rtl/submodules/alu/alu_tb.v
module alu_tb();
parameter W = 3;
reg [W-1:0] tb_a, tb_b;
reg tb_clk, tb_en_a, tb_en_b, tb_en_res, tb_a_out, tb_add_sub;
reg [11:0] test_vectors [0:5];
wire [W-1:0] tb_result;
wire tb_carry_flag, tb_zero_flag;
wire [W-1:0] tb_a_result; // To observe the output of a_result from the ALU, which will allow us to verify that the tri-state buffer controlling the output of a is functioning correctly and that the value of a is being captured and output as expected.

reg tb_reset; // To provide a reset signal to the ALU, which can be used to initialize the internal state of the ALU and ensure that it starts from a known state for each test case. This can help to improve the reliability and consistency of the test results by ensuring that any previous state or values do not affect the current test case.

reg [W-1:0] expected_result; // To hold the expected result for each test case, which will be compared against the actual output from the ALU to verify correctness.

reg expected_carry_flag; // To hold the expected value of the carry flag for each test case, which will be compared against the actual carry flag output from the ALU to verify correctness.

reg expected_zero_flag; // To hold the expected value of the zero flag for each test case, which will be compared against the actual zero flag output from the ALU to verify correctness.

  integer i; // An integer variable to be used as a loop counter for iterating through the test cases in the test vector array.

always #5 tb_clk = ~tb_clk; // Clock generation: Toggle the clock every 5 time units to create a clock signal for the ALU.

alu #(.WIDTH(W)) dut (.clk(tb_clk), .a(tb_a), .b(tb_b), .reset_sig(tb_reset), .en_a(tb_en_a), .en_b(tb_en_b), .en_res(tb_en_res), .add_sub(tb_add_sub), .result(tb_result), .a_result(tb_a_result), .carry_flag(tb_carry_flag), .a_out(tb_a_out), .zero_flag(tb_zero_flag));

initial begin 
  $dumpfile("sim/alu/alu.vcd");
  $dumpvars(0, alu_tb);
  $readmemb("rtl/submodules/alu/alu.tv", test_vectors);
 
// 1. Initialize Everything
    tb_clk = 0;
    expected_result = 0;
    expected_carry_flag = 0;
    expected_zero_flag = 0;
    tb_reset = 1; // Start in reset
    tb_en_a = 0; tb_en_b = 0; tb_en_res = 0; tb_a_out = 0;
    tb_a = {W{1'b0}}; tb_b = {W{1'b0}}; tb_add_sub = 0;
    i = 0;
    #15;          // Hold reset for more than one clock cycle
    tb_reset = 0; // Release reset
    #10;

  // Test addition
   for (i = 0; i < 6; i = i + 1) begin 
    {tb_a, tb_b, tb_add_sub, expected_carry_flag, expected_zero_flag, expected_result} = test_vectors[i]; // Split the test vector into inputs and expected output

    tb_en_a = 1; // Enable loading of a
    tb_en_b = 1; // Enable loading of b

    @ (posedge tb_clk); // Wait for the positive edge of the clock to ensure that the inputs are registered in the ALU before checking the output

    tb_en_res = 1; // Enable output of result
    tb_a_out = 1; // Enable output of a_result to observe the value of a being captured and output by the ALU

    #2; // Wait for a short time after the clock edge to allow the outputs to stabilize before checking them
   
   if ((tb_result !== expected_result) || (tb_carry_flag !== expected_carry_flag) || (tb_zero_flag !== expected_zero_flag)) begin 
      $display("Test Case %d failed: a = %b, b = %b, add_sub = %b, tb_carry_flag = %b, tb_zero_flag = %b, expected_carry_flag = %b, expected_zero_flag = %b, Expected Result = %b, Actual Result = %b", i, tb_a, tb_b, tb_add_sub, tb_carry_flag, tb_zero_flag, expected_carry_flag, expected_zero_flag, expected_result, tb_result);
    end else begin 
      $display("Test Case %d passed: a = %b, b = %b, add_sub = %b, Result = %b", i, tb_a, tb_b, tb_add_sub, tb_result);
    end

    if (tb_a_result !== tb_a) begin
       $display("Test failed: a_result should match a when en_a is 1 and a_out is 1"); 
       end 
       else begin 
        $display("a_result correctly matches a: %b", tb_a_result);
         end

    #3; // Wait for a short time to test register "holding" power
    tb_en_a = 0; // Disable loading of a for the next test case
    tb_en_b = 0; // Disable loading of b for the next test case
    tb_en_res = 0; // Disable output of result for the next test case
    tb_a_out = 0; // Disable output of a_result for the next test case
   end
    $display("All test cases completed");
    $finish;
   end
 endmodule

sim/alu/alu.vcd
$date
	Wed May 13 13:14:13 2026
$end
$version
	Icarus Verilog
$end
$timescale
	1s
$end
$scope module alu_tb $end
$var wire 1 ! tb_zero_flag $end
$var wire 3 " tb_result [2:0] $end
$var wire 1 # tb_carry_flag $end
$var wire 3 $ tb_a_result [2:0] $end
$var parameter 32 % W $end
$var reg 1 & expected_carry_flag $end
$var reg 3 ' expected_result [2:0] $end
$var reg 1 ( expected_zero_flag $end
$var reg 3 ) tb_a [2:0] $end
$var reg 1 * tb_a_out $end
$var reg 1 + tb_add_sub $end
$var reg 3 , tb_b [2:0] $end
$var reg 1 - tb_clk $end
$var reg 1 . tb_en_a $end
$var reg 1 / tb_en_b $end
$var reg 1 0 tb_en_res $end
$var reg 1 1 tb_reset $end
$var integer 32 2 i [31:0] $end
$scope module dut $end
$var wire 3 3 a [2:0] $end
$var wire 1 * a_out $end
$var wire 1 + add_sub $end
$var wire 3 4 b [2:0] $end
$var wire 1 - clk $end
$var wire 1 . en_a $end
$var wire 1 / en_b $end
$var wire 1 0 en_res $end
$var wire 1 1 reset_sig $end
$var wire 3 5 xor_intern_b [2:0] $end
$var wire 3 6 result [2:0] $end
$var wire 3 7 internal_sum [2:0] $end
$var wire 3 8 intern_b [2:0] $end
$var wire 3 9 intern_a [2:0] $end
$var wire 4 : carry [3:0] $end
$var wire 3 ; a_result [2:0] $end
$var parameter 32 < WIDTH $end
$var reg 1 # carry_flag $end
$var reg 1 ! zero_flag $end
$scope begin en_flip_flop[0] $end
$var parameter 2 = i $end
$scope module a_input $end
$var wire 1 - clk $end
$var wire 1 > d $end
$var wire 1 . en $end
$var wire 1 1 reset $end
$var parameter 32 ? WIDTH $end
$var reg 1 @ q $end
$upscope $end
$scope module a_output $end
$var wire 1 A a $end
$var wire 1 * en $end
$var wire 1 B y $end
$var parameter 32 C WIDTH $end
$upscope $end
$scope module b_input $end
$var wire 1 - clk $end
$var wire 1 D d $end
$var wire 1 / en $end
$var wire 1 1 reset $end
$var parameter 32 E WIDTH $end
$var reg 1 F q $end
$upscope $end
$scope module fa $end
$var wire 1 G a $end
$var wire 1 H b $end
$var wire 1 I cin $end
$var reg 1 J cout $end
$var reg 1 K g $end
$var reg 1 L p $end
$var reg 1 M sum $end
$upscope $end
$scope module res_output $end
$var wire 1 N a $end
$var wire 1 0 en $end
$var wire 1 O y $end
$var parameter 32 P WIDTH $end
$upscope $end
$upscope $end
$scope begin en_flip_flop[1] $end
$var parameter 2 Q i $end
$scope module a_input $end
$var wire 1 - clk $end
$var wire 1 R d $end
$var wire 1 . en $end
$var wire 1 1 reset $end
$var parameter 32 S WIDTH $end
$var reg 1 T q $end
$upscope $end
$scope module a_output $end
$var wire 1 U a $end
$var wire 1 * en $end
$var wire 1 V y $end
$var parameter 32 W WIDTH $end
$upscope $end
$scope module b_input $end
$var wire 1 - clk $end
$var wire 1 X d $end
$var wire 1 / en $end
$var wire 1 1 reset $end
$var parameter 32 Y WIDTH $end
$var reg 1 Z q $end
$upscope $end
$scope module fa $end
$var wire 1 [ a $end
$var wire 1 \ b $end
$var wire 1 ] cin $end
$var reg 1 ^ cout $end
$var reg 1 _ g $end
$var reg 1 ` p $end
$var reg 1 a sum $end
$upscope $end
$scope module res_output $end
$var wire 1 b a $end
$var wire 1 0 en $end
$var wire 1 c y $end
$var parameter 32 d WIDTH $end
$upscope $end
$upscope $end
$scope begin en_flip_flop[2] $end
$var parameter 3 e i $end
$scope module a_input $end
$var wire 1 - clk $end
$var wire 1 f d $end
$var wire 1 . en $end
$var wire 1 1 reset $end
$var parameter 32 g WIDTH $end
$var reg 1 h q $end
$upscope $end
$scope module a_output $end
$var wire 1 i a $end
$var wire 1 * en $end
$var wire 1 j y $end
$var parameter 32 k WIDTH $end
$upscope $end
$scope module b_input $end
$var wire 1 - clk $end
$var wire 1 l d $end
$var wire 1 / en $end
$var wire 1 1 reset $end
$var parameter 32 m WIDTH $end
$var reg 1 n q $end
$upscope $end
$scope module fa $end
$var wire 1 o a $end
$var wire 1 p b $end
$var wire 1 q cin $end
$var reg 1 r cout $end
$var reg 1 s g $end
$var reg 1 t p $end
$var reg 1 u sum $end
$upscope $end
$scope module res_output $end
$var wire 1 v a $end
$var wire 1 0 en $end
$var wire 1 w y $end
$var parameter 32 x WIDTH $end
$upscope $end
$upscope $end
$upscope $end
$upscope $end
$enddefinitions $end
$comment Show the parameter values. $end
$dumpall
b1 x
b1 m
b1 k
b1 g
b10 e
b1 d
b1 Y
b1 W
b1 S
b1 Q
b1 P
b1 E
b1 C
b1 ?
b0 =
b11 <
b11 %
$end
#0
$dumpvars
zw
0v
0u
0t
0s
0r
0q
0p
0o
0n
0l
zj
0i
0h
0f
zc
0b
0a
0`
0_
0^
0]
0\
0[
0Z
0X
zV
0U
0T
0R
zO
0N
0M
0L
0K
0J
0I
0H
0G
0F
0D
zB
0A
0@
0>
bz ;
b0 :
b0 9
b0 8
b0 7
bz 6
b0 5
b0 4
b0 3
b0 2
11
00
0/
0.
0-
b0 ,
0+
0*
b0 )
0(
b0 '
0&
bz $
0#
bz "
1!
$end
#5
1-
#10
0-
#15
1-
01
#20
0-
#25
1N
0!
b1 7
1M
1L
1H
b1 8
b1 5
1F
0B
0V
b0 $
b0 ;
0j
1O
0c
b1 "
b1 6
0w
1*
10
1D
1-
1/
1.
b1 ,
b1 4
b1 '
#30
1>
0D
1X
zB
zV
bz $
bz ;
zj
zO
zc
bz "
bz 6
zw
b1 )
b1 3
b10 ,
b10 4
b11 '
b1 2
0*
00
1/
1.
0-
#35
1b
0v
1a
0u
0q
0^
1`
0]
1N
0!
0H
1\
b0 :
0J
b11 7
1M
0K
1L
b10 8
1G
1A
b1 9
1@
0F
b10 5
1Z
1B
0V
b1 $
b1 ;
0j
1O
1c
b11 "
b11 6
0w
1*
10
1-
#40
1b
1v
1]
1a
0`
b111 7
1u
1t
1J
1K
0L
1H
0\
1p
0>
1R
1D
0X
1I
b101 8
zB
zV
bz $
bz ;
zj
zO
zc
bz "
bz 6
zw
b10 )
b10 3
b1 ,
b1 4
b11 :
1+
1&
b1 '
b10 2
0*
00
1/
1.
0-
#45
0v
0]
1#
1_
1r
0u
0J
1\
1q
0b
0H
1N
b1101 :
1^
0a
0`
b110 8
b1 7
1M
0K
0L
1[
1U
0G
0A
0Z
1T
b1 5
1F
b10 9
0@
0B
1V
b10 $
b10 ;
0j
1O
0c
b1 "
b1 6
0w
1*
10
1-
#50
1>
zB
zV
bz $
bz ;
zj
zO
zc
bz "
bz 6
zw
b11 )
b11 3
b10 '
b11 2
0*
00
1/
1.
0-
#55
1b
1a
1]
0N
0!
b1111 :
1J
b10 7
0M
1L
1G
1A
b11 9
1@
1B
1V
b11 $
b11 ;
0j
0O
1c
b10 "
b10 6
0w
1*
10
1-
#60
0b
1v
0#
0a
0_
1`
0r
b100 7
1u
0t
1K
0L
1H
0\
0p
0>
0R
0D
0I
b1 8
zB
zV
bz $
bz ;
zj
zO
zc
bz "
bz 6
zw
b0 )
b0 3
b0 ,
b0 4
b110 :
0+
0&
1(
b0 '
b100 2
0*
00
1/
1.
0-
#65
0v
1!
0u
0q
0b
0H
0]
0N
0^
0a
0`
b0 8
b0 :
0J
b0 7
0M
0K
0L
0[
0U
0G
0A
0T
b0 5
0F
b0 9
0@
0B
0V
b0 $
b0 ;
0j
0O
0c
b0 "
b0 6
0w
1*
10
1-
#70
1>
1R
1f
1D
1X
1l
zB
zV
bz $
bz ;
zj
zO
zc
bz "
bz 6
zw
b111 )
b111 3
b111 ,
b111 4
1&
0(
b110 '
b101 2
0*
00
1/
1.
0-
#75
1]
1q
1#
1J
1K
1^
1_
b1110 :
1r
1s
0N
1H
1b
1\
1v
0!
1p
0M
0L
1a
0`
b110 7
1u
0t
b111 8
1G
1A
1[
1U
1i
1o
1@
1F
1T
1Z
b111 9
1h
b111 5
1n
1B
1V
b111 $
b111 ;
1j
0O
1c
b110 "
b110 6
1w
1*
10
1-
#80
zB
zV
bz $
bz ;
zj
zO
zc
bz "
bz 6
zw
b110 2
0*
00
0/
0.
0-
