rtl/lib/tristate_buff_n/tristate_buff_n.v
`timescale 1ns/1ps

module tristate_buff_n #(parameter WIDTH = 1) (input en, input [WIDTH-1:0] a, output [WIDTH-1:0] y);
assign y = en ? a :{WIDTH{1'bz}};
endmodule

rtl/lib/gates/and/and_n.v
module  and_n #(parameter WIDTH = 2) (input [WIDTH-1:0] a, output y); // ports for the and_n module, we have a parameter WIDTH that determines how many inputs we have, and one output y which will be the result of the AND operation on all the inputs.

  assign y = &a; // the output y is assigned the result of the bitwise AND operation on all the inputs. This means y will be 1 only if all inputs are 1, otherwise it will be 0.

endmodule

rtl/lib/async_resettable_dff/async_resettable_dff.v
`timescale 1ns/1ps

module async_resettable_dff #(parameter WIDTH = 1) (input clk, input reset, input [WIDTH-1:0] d, output reg [WIDTH-1:0] q);

always @ (posedge clk, posedge reset) begin 
   if (reset) begin 
      q <= 0; // If the reset signal is asserted (active high), set the output q to 0. This is a common behavior for flip-flops, where the reset signal initializes the output to a known state.
   end else begin 
    q <= d; // on the rising edge of the clock, assign the value of d to q. The non-blocking assignment (<=) is used to ensure that the value of q is updated at the end of the current time step, allowing for proper synchronization with the clock signal.
   end
end

endmodule

rtl/lib/memory_row/memory_row.v
module memory_row #(parameter DATA_W = 8) (input decoder_output_line, input ram_out_sel, input ram_in_sel, input [DATA_W-1:0] data_in, output [DATA_W-1:0] mem_row_y);

wire ram_in_decoder_line_output;
wire [DATA_W-1:0] memory_cell_output;
wire [DATA_W-1:0] memory_cell_and_gate_output;

and_n #(.WIDTH(2)) ram_in_control_inst (.a({decoder_output_line, ram_in_sel}), .y(ram_in_decoder_line_output));

genvar i;
generate 
 for (i = 0; i < DATA_W; i = i + 1) begin: gen_memory_cell 
  async_resettable_dff #(.WIDTH(1)) memory_cell_inst (.clk(ram_in_decoder_line_output), .reset(1'b0), .d(data_in[i]), .q(memory_cell_output[i]));

  and_n #(.WIDTH(2)) and_inst (.a({memory_cell_output[i], decoder_output_line}), .y(memory_cell_and_gate_output[i]));

  tristate_buff_n #(.WIDTH(1)) tristate_inst (.en(ram_out_sel), .a(memory_cell_and_gate_output[i]), .y(mem_row_y[i]));

 end
endgenerate 
  
endmodule

rtl/lib/memory_row/memory_row_tb.v
`timescale 1ns/1ps

module memory_row_tb();
parameter D = 8;

reg tb_decoder_output_line;
reg tb_ram_out_sel;
reg tb_ram_in_sel;
reg [D-1:0] tb_data_in;
reg [15:0] test_vectors [0:3];

reg [D-1:0] expected_y;
wire [D-1:0] tb_mem_row_y;

memory_row #(.DATA_W(D)) dut (.decoder_output_line(tb_decoder_output_line), .ram_in_sel(tb_ram_in_sel), .ram_out_sel(tb_ram_out_sel), .data_in(tb_data_in), .mem_row_y(tb_mem_row_y));

integer i;  
initial begin 
 $dumpfile("sim/memory_row/memory_row.vcd");
 $dumpvars(0, memory_row_tb);
 $readmemb("rtl/lib/memory_row/memory_row.tv", test_vectors);

  // initial value when the simulation starts
   tb_decoder_output_line = 0;
   expected_y = {D{1'b0}};
   tb_ram_in_sel = 0;
   tb_ram_out_sel = 0;

 for (i = 0; i < 4; i = i + 1) begin 
   
   {tb_data_in, expected_y} = test_vectors[i];
    
    #1; // Setup time 
    tb_decoder_output_line = 1;
    tb_ram_in_sel = 1;
    tb_ram_out_sel = 1;
    #9;
    
    if (expected_y !== tb_mem_row_y) begin 
      $display("Test %0d Failed: Expected y = %b, Actual y = %b", i, expected_y, tb_mem_row_y);
    end else begin 
      $display("Test %0d Passed: Expected y = %b, Actual y = %b", i, expected_y, tb_mem_row_y);
    end

    tb_decoder_output_line = 0;
    tb_ram_in_sel = 0;
    tb_ram_out_sel = 0;
    #10;
 end
 $display("All Test cases completed.");
 $finish;
end
endmodule

sim/memory_row/memory_row.vcd
$date
	Mon May 18 13:39:09 2026
$end
$version
	Icarus Verilog
$end
$timescale
	1ps
$end
$scope module memory_row_tb $end
$var wire 8 ! tb_mem_row_y [7:0] $end
$var parameter 32 " D $end
$var reg 8 # expected_y [7:0] $end
$var reg 8 $ tb_data_in [7:0] $end
$var reg 1 % tb_decoder_output_line $end
$var reg 1 & tb_ram_in_sel $end
$var reg 1 ' tb_ram_out_sel $end
$var integer 32 ( i [31:0] $end
$scope module dut $end
$var wire 8 ) data_in [7:0] $end
$var wire 1 % decoder_output_line $end
$var wire 1 & ram_in_sel $end
$var wire 1 ' ram_out_sel $end
$var wire 1 * ram_in_decoder_line_output $end
$var wire 8 + memory_cell_output [7:0] $end
$var wire 8 , memory_cell_and_gate_output [7:0] $end
$var wire 8 - mem_row_y [7:0] $end
$var parameter 32 . DATA_W $end
$scope begin gen_memory_cell[0] $end
$var parameter 2 / i $end
$scope module and_inst $end
$var wire 2 0 a [1:0] $end
$var wire 1 1 y $end
$var parameter 32 2 WIDTH $end
$upscope $end
$scope module memory_cell_inst $end
$var wire 1 3 d $end
$var wire 1 4 reset $end
$var wire 1 * clk $end
$var parameter 32 5 WIDTH $end
$var reg 1 6 q $end
$upscope $end
$scope module tristate_inst $end
$var wire 1 7 a $end
$var wire 1 ' en $end
$var wire 1 8 y $end
$var parameter 32 9 WIDTH $end
$upscope $end
$upscope $end
$scope begin gen_memory_cell[1] $end
$var parameter 2 : i $end
$scope module and_inst $end
$var wire 2 ; a [1:0] $end
$var wire 1 < y $end
$var parameter 32 = WIDTH $end
$upscope $end
$scope module memory_cell_inst $end
$var wire 1 > d $end
$var wire 1 ? reset $end
$var wire 1 * clk $end
$var parameter 32 @ WIDTH $end
$var reg 1 A q $end
$upscope $end
$scope module tristate_inst $end
$var wire 1 B a $end
$var wire 1 ' en $end
$var wire 1 C y $end
$var parameter 32 D WIDTH $end
$upscope $end
$upscope $end
$scope begin gen_memory_cell[2] $end
$var parameter 3 E i $end
$scope module and_inst $end
$var wire 2 F a [1:0] $end
$var wire 1 G y $end
$var parameter 32 H WIDTH $end
$upscope $end
$scope module memory_cell_inst $end
$var wire 1 I d $end
$var wire 1 J reset $end
$var wire 1 * clk $end
$var parameter 32 K WIDTH $end
$var reg 1 L q $end
$upscope $end
$scope module tristate_inst $end
$var wire 1 M a $end
$var wire 1 ' en $end
$var wire 1 N y $end
$var parameter 32 O WIDTH $end
$upscope $end
$upscope $end
$scope begin gen_memory_cell[3] $end
$var parameter 3 P i $end
$scope module and_inst $end
$var wire 2 Q a [1:0] $end
$var wire 1 R y $end
$var parameter 32 S WIDTH $end
$upscope $end
$scope module memory_cell_inst $end
$var wire 1 T d $end
$var wire 1 U reset $end
$var wire 1 * clk $end
$var parameter 32 V WIDTH $end
$var reg 1 W q $end
$upscope $end
$scope module tristate_inst $end
$var wire 1 X a $end
$var wire 1 ' en $end
$var wire 1 Y y $end
$var parameter 32 Z WIDTH $end
$upscope $end
$upscope $end
$scope begin gen_memory_cell[4] $end
$var parameter 4 [ i $end
$scope module and_inst $end
$var wire 2 \ a [1:0] $end
$var wire 1 ] y $end
$var parameter 32 ^ WIDTH $end
$upscope $end
$scope module memory_cell_inst $end
$var wire 1 _ d $end
$var wire 1 ` reset $end
$var wire 1 * clk $end
$var parameter 32 a WIDTH $end
$var reg 1 b q $end
$upscope $end
$scope module tristate_inst $end
$var wire 1 c a $end
$var wire 1 ' en $end
$var wire 1 d y $end
$var parameter 32 e WIDTH $end
$upscope $end
$upscope $end
$scope begin gen_memory_cell[5] $end
$var parameter 4 f i $end
$scope module and_inst $end
$var wire 2 g a [1:0] $end
$var wire 1 h y $end
$var parameter 32 i WIDTH $end
$upscope $end
$scope module memory_cell_inst $end
$var wire 1 j d $end
$var wire 1 k reset $end
$var wire 1 * clk $end
$var parameter 32 l WIDTH $end
$var reg 1 m q $end
$upscope $end
$scope module tristate_inst $end
$var wire 1 n a $end
$var wire 1 ' en $end
$var wire 1 o y $end
$var parameter 32 p WIDTH $end
$upscope $end
$upscope $end
$scope begin gen_memory_cell[6] $end
$var parameter 4 q i $end
$scope module and_inst $end
$var wire 2 r a [1:0] $end
$var wire 1 s y $end
$var parameter 32 t WIDTH $end
$upscope $end
$scope module memory_cell_inst $end
$var wire 1 u d $end
$var wire 1 v reset $end
$var wire 1 * clk $end
$var parameter 32 w WIDTH $end
$var reg 1 x q $end
$upscope $end
$scope module tristate_inst $end
$var wire 1 y a $end
$var wire 1 ' en $end
$var wire 1 z y $end
$var parameter 32 { WIDTH $end
$upscope $end
$upscope $end
$scope begin gen_memory_cell[7] $end
$var parameter 4 | i $end
$scope module and_inst $end
$var wire 2 } a [1:0] $end
$var wire 1 ~ y $end
$var parameter 32 !" WIDTH $end
$upscope $end
$scope module memory_cell_inst $end
$var wire 1 "" d $end
$var wire 1 #" reset $end
$var wire 1 * clk $end
$var parameter 32 $" WIDTH $end
$var reg 1 %" q $end
$upscope $end
$scope module tristate_inst $end
$var wire 1 &" a $end
$var wire 1 ' en $end
$var wire 1 '" y $end
$var parameter 32 (" WIDTH $end
$upscope $end
$upscope $end
$scope module ram_in_control_inst $end
$var wire 2 )" a [1:0] $end
$var wire 1 * y $end
$var parameter 32 *" WIDTH $end
$upscope $end
$upscope $end
$upscope $end
$enddefinitions $end
$comment Show the parameter values. $end
$dumpall
b10 *"
b1 ("
b1 $"
b10 !"
b111 |
b1 {
b1 w
b10 t
b110 q
b1 p
b1 l
b10 i
b101 f
b1 e
b1 a
b10 ^
b100 [
b1 Z
b1 V
b10 S
b11 P
b1 O
b1 K
b10 H
b10 E
b1 D
b1 @
b10 =
b1 :
b1 9
b1 5
b10 2
b0 /
b1000 .
b1000 "
$end
#0
$dumpvars
b0 )"
z'"
0&"
x%"
0#"
1""
0~
bx0 }
zz
0y
xx
0v
0u
0s
bx0 r
zo
0n
xm
0k
0j
0h
bx0 g
zd
0c
xb
0`
0_
0]
bx0 \
zY
0X
xW
0U
1T
0R
bx0 Q
zN
0M
xL
0J
0I
0G
bx0 F
zC
0B
xA
0?
0>
0<
bx0 ;
z8
07
x6
04
03
01
bx0 0
bz -
b0 ,
bx +
0*
b10001000 )
b0 (
0'
0&
0%
b10001000 $
b10001000 #
bz !
$end
#1000
06
0A
0L
1W
0b
0m
0x
b10001000 +
1%"
08
0C
0N
1Y
0d
0o
0z
b10001000 !
b10001000 -
1'"
07
0B
0M
1X
0c
0n
0y
1&"
1'
1*
1&
b11 )"
01
b1 0
0<
b1 ;
0G
b1 F
1R
b11 Q
0]
b1 \
0h
b1 g
0s
b1 r
b10001000 ,
1~
b11 }
1%
#10000
z8
zC
zN
zY
zd
zo
zz
bz !
bz -
z'"
0X
0&"
0'
0&
0*
b0 )"
b0 0
b0 ;
b0 F
0R
b10 Q
b0 \
b0 g
b0 r
b0 ,
0~
b10 }
0%
#20000
0T
1_
1j
1u
b11110000 $
b11110000 )
b11110000 #
b1 (
#21000
1c
1n
1y
1]
1h
1s
0W
1b
1m
b11110000 +
1x
08
0C
0N
0Y
1d
1o
1z
b11110000 !
b11110000 -
1'"
0X
1&"
1'
1*
1&
b11 )"
b1 0
b1 ;
b1 F
0R
b1 Q
b11 \
b11 g
b11 r
b11110000 ,
1~
b11 }
1%
#30000
z8
zC
zN
zY
zd
zo
zz
bz !
bz -
z'"
0c
0n
0y
0&"
0'
0&
0*
b0 )"
b0 0
b0 ;
b0 F
b0 Q
0]
b10 \
0h
b10 g
0s
b10 r
b0 ,
0~
b10 }
0%
#40000
13
1I
0j
0""
b1010101 $
b1010101 )
b1010101 #
b10 (
#41000
17
1M
11
1G
16
1L
0m
b1010101 +
0%"
18
0C
1N
0Y
1d
0o
1z
b1010101 !
b1010101 -
0'"
1c
0n
1y
0&"
1'
1*
1&
b11 )"
b11 0
b1 ;
b11 F
b1 Q
1]
b11 \
0h
b1 g
1s
b11 r
b1010101 ,
0~
b1 }
1%
#50000
z8
zC
zN
zY
zd
zo
zz
bz !
bz -
z'"
07
0M
0c
0y
0'
0&
0*
b0 )"
01
b10 0
b0 ;
0G
b10 F
b0 Q
0]
b10 \
b0 g
b0 ,
0s
b10 r
b0 }
0%
#60000
03
1T
0_
1""
b11001100 $
b11001100 )
b11001100 #
b11 (
#61000
1X
1&"
1R
1~
06
1W
0b
b11001100 +
1%"
08
0C
1N
1Y
0d
0o
1z
b11001100 !
b11001100 -
1'"
07
1M
0c
1y
1'
1*
1&
b11 )"
01
b1 0
b1 ;
1G
b11 F
b11 Q
0]
b1 \
b1 g
b11001100 ,
1s
b11 r
b11 }
1%
#70000
z8
zC
zN
zY
zd
zo
zz
bz !
bz -
z'"
0M
0X
0y
0&"
0'
0&
0*
b0 )"
b0 0
b0 ;
0G
b10 F
0R
b10 Q
b0 \
b0 g
0s
b10 r
b0 ,
0~
b10 }
0%
#80000
b100 (
