rtl/lib/en_dff/en_dff.v
`timescale 1ns/1ps

module en_dff #(parameter WIDTH = 1) (input en, input clk, input reset, input [WIDTH-1:0] d, output reg q);

always @ (posedge clk, posedge reset) 
  if (en) begin 
   q <= d;
  end else if (reset) begin 
    q <= 0;
  end
  
endmodule

rtl/lib/gates/and/and_n.v
`timescale 1ns/1ps

module  and_n #(parameter WIDTH = 2) (input [WIDTH-1:0] a, output y); // ports for the and_n module, we have a parameter WIDTH that determines how many inputs we have, and one output y which will be the result of the AND operation on all the inputs.

  assign y = &a; // the output y is assigned the result of the bitwise AND operation on all the inputs. This means y will be 1 only if all inputs are 1, otherwise it will be 0.

endmodule

rtl/lib/memory_row/memory_row.v
`timescale 1ns/1ps

module memory_row #(parameter DATA_W = 8) (
    input clk,
    input reset_sig,
    input decoder_output_line,  
    input ram_in_sel, 
    input [DATA_W-1:0] data_in, 
    
    output [DATA_W-1:0] mem_row_y
);

wire row_write_enable;
wire [DATA_W-1:0] memory_cell_output;


// Write Control Gate
and_n #(.WIDTH(2)) ram_in_control_inst (.a({decoder_output_line, ram_in_sel}), .y(row_write_enable));

genvar i;
generate 
    for (i = 0; i < DATA_W; i = i + 1) begin: gen_memory_cell 

        en_dff #(.WIDTH(1)) memory_cell_inst (
            .clk(clk), 
            .en(row_write_enable),
            .reset(reset_sig), 
            .d(data_in[i]), 
            .q(memory_cell_output[i])
        );

            // If row is selected, output the cell data. Otherwise, output 0.
        assign mem_row_y[i] = decoder_output_line ? memory_cell_output[i] : 1'b0;
    end
endgenerate 
  
endmodule

rtl/lib/memory_row/memory_row_tb.v
`timescale 1ns/1ps

module memory_row_tb();
parameter D = 8;

reg tb_clk;
reg tb_reset_sig;
reg tb_decoder_output_line;
reg tb_ram_in_sel;
reg [D-1:0] tb_data_in;
reg [15:0] test_vectors [0:3];

reg [D-1:0] expected_y;
wire [D-1:0] tb_mem_row_y;

memory_row #(.DATA_W(D)) dut (
  .clk(tb_clk), 
  .reset_sig(tb_reset_sig), 
  .decoder_output_line(tb_decoder_output_line), 
  .ram_in_sel(tb_ram_in_sel), 
  .data_in(tb_data_in), 
  .mem_row_y(tb_mem_row_y)
);

initial tb_clk = 0;
always #5 tb_clk = ~tb_clk; // 10ns clock period
integer i;  
initial begin 
 $dumpfile("sim/memory_row/memory_row.vcd");
 $dumpvars(0, memory_row_tb);
 $readmemb("rtl/lib/memory_row/memory_row.tv", test_vectors);

  // initial value when the simulation starts
   tb_decoder_output_line = 0;
   expected_y = {D{1'b0}};
   tb_ram_in_sel = 0;
   tb_reset_sig = 1;
    #10; // Wait for 10ns to ensure reset is applied
    tb_reset_sig = 0; // Deassert reset after 10ns
    
 for (i = 0; i < 4; i = i + 1) begin 
   
   {tb_data_in, expected_y} = test_vectors[i];
    
    #1; // Setup time 
    tb_decoder_output_line = 1;
    tb_ram_in_sel = 1;
    #9;
    
    if (expected_y !== tb_mem_row_y) begin 
      $display("Test %0d Failed: Expected y = %b, Actual y = %b", i, expected_y, tb_mem_row_y);
    end else begin 
      $display("Test %0d Passed: Expected y = %b, Actual y = %b", i, expected_y, tb_mem_row_y);
    end

    tb_decoder_output_line = 0;
    tb_ram_in_sel = 0;
    #10;
 end
 $display("All Test cases completed.");
 $finish;
end
endmodule

sim/memory_row/memory_row.vcd
$date
	Fri May 22 13:14:25 2026
$end
$version
	Icarus Verilog
$end
$timescale
	1ps
$end
$scope module memory_row_tb $end
$var wire 8 ! tb_mem_row_y [7:0] $end
$var parameter 32 " D $end
$var reg 8 # expected_y [7:0] $end
$var reg 1 $ tb_clk $end
$var reg 8 % tb_data_in [7:0] $end
$var reg 1 & tb_decoder_output_line $end
$var reg 1 ' tb_ram_in_sel $end
$var reg 1 ( tb_reset_sig $end
$var integer 32 ) i [31:0] $end
$scope module dut $end
$var wire 1 $ clk $end
$var wire 8 * data_in [7:0] $end
$var wire 1 & decoder_output_line $end
$var wire 1 ' ram_in_sel $end
$var wire 1 ( reset_sig $end
$var wire 1 + row_write_enable $end
$var wire 8 , memory_cell_output [7:0] $end
$var wire 8 - mem_row_y [7:0] $end
$var parameter 32 . DATA_W $end
$scope begin gen_memory_cell[0] $end
$var parameter 2 / i $end
$scope module memory_cell_inst $end
$var wire 1 $ clk $end
$var wire 1 0 d $end
$var wire 1 ( reset $end
$var wire 1 + en $end
$var parameter 32 1 WIDTH $end
$var reg 1 2 q $end
$upscope $end
$scope module tristate_inst $end
$var wire 1 3 a $end
$var wire 1 & en $end
$var wire 1 4 y $end
$var parameter 32 5 WIDTH $end
$upscope $end
$upscope $end
$scope begin gen_memory_cell[1] $end
$var parameter 2 6 i $end
$scope module memory_cell_inst $end
$var wire 1 $ clk $end
$var wire 1 7 d $end
$var wire 1 ( reset $end
$var wire 1 + en $end
$var parameter 32 8 WIDTH $end
$var reg 1 9 q $end
$upscope $end
$scope module tristate_inst $end
$var wire 1 : a $end
$var wire 1 & en $end
$var wire 1 ; y $end
$var parameter 32 < WIDTH $end
$upscope $end
$upscope $end
$scope begin gen_memory_cell[2] $end
$var parameter 3 = i $end
$scope module memory_cell_inst $end
$var wire 1 $ clk $end
$var wire 1 > d $end
$var wire 1 ( reset $end
$var wire 1 + en $end
$var parameter 32 ? WIDTH $end
$var reg 1 @ q $end
$upscope $end
$scope module tristate_inst $end
$var wire 1 A a $end
$var wire 1 & en $end
$var wire 1 B y $end
$var parameter 32 C WIDTH $end
$upscope $end
$upscope $end
$scope begin gen_memory_cell[3] $end
$var parameter 3 D i $end
$scope module memory_cell_inst $end
$var wire 1 $ clk $end
$var wire 1 E d $end
$var wire 1 ( reset $end
$var wire 1 + en $end
$var parameter 32 F WIDTH $end
$var reg 1 G q $end
$upscope $end
$scope module tristate_inst $end
$var wire 1 H a $end
$var wire 1 & en $end
$var wire 1 I y $end
$var parameter 32 J WIDTH $end
$upscope $end
$upscope $end
$scope begin gen_memory_cell[4] $end
$var parameter 4 K i $end
$scope module memory_cell_inst $end
$var wire 1 $ clk $end
$var wire 1 L d $end
$var wire 1 ( reset $end
$var wire 1 + en $end
$var parameter 32 M WIDTH $end
$var reg 1 N q $end
$upscope $end
$scope module tristate_inst $end
$var wire 1 O a $end
$var wire 1 & en $end
$var wire 1 P y $end
$var parameter 32 Q WIDTH $end
$upscope $end
$upscope $end
$scope begin gen_memory_cell[5] $end
$var parameter 4 R i $end
$scope module memory_cell_inst $end
$var wire 1 $ clk $end
$var wire 1 S d $end
$var wire 1 ( reset $end
$var wire 1 + en $end
$var parameter 32 T WIDTH $end
$var reg 1 U q $end
$upscope $end
$scope module tristate_inst $end
$var wire 1 V a $end
$var wire 1 & en $end
$var wire 1 W y $end
$var parameter 32 X WIDTH $end
$upscope $end
$upscope $end
$scope begin gen_memory_cell[6] $end
$var parameter 4 Y i $end
$scope module memory_cell_inst $end
$var wire 1 $ clk $end
$var wire 1 Z d $end
$var wire 1 ( reset $end
$var wire 1 + en $end
$var parameter 32 [ WIDTH $end
$var reg 1 \ q $end
$upscope $end
$scope module tristate_inst $end
$var wire 1 ] a $end
$var wire 1 & en $end
$var wire 1 ^ y $end
$var parameter 32 _ WIDTH $end
$upscope $end
$upscope $end
$scope begin gen_memory_cell[7] $end
$var parameter 4 ` i $end
$scope module memory_cell_inst $end
$var wire 1 $ clk $end
$var wire 1 a d $end
$var wire 1 ( reset $end
$var wire 1 + en $end
$var parameter 32 b WIDTH $end
$var reg 1 c q $end
$upscope $end
$scope module tristate_inst $end
$var wire 1 d a $end
$var wire 1 & en $end
$var wire 1 e y $end
$var parameter 32 f WIDTH $end
$upscope $end
$upscope $end
$scope module ram_in_control_inst $end
$var wire 2 g a [1:0] $end
$var wire 1 + y $end
$var parameter 32 h WIDTH $end
$upscope $end
$upscope $end
$upscope $end
$enddefinitions $end
$comment Show the parameter values. $end
$dumpall
b10 h
b1 f
b1 b
b111 `
b1 _
b1 [
b110 Y
b1 X
b1 T
b101 R
b1 Q
b1 M
b100 K
b1 J
b1 F
b11 D
b1 C
b1 ?
b10 =
b1 <
b1 8
b1 6
b1 5
b1 1
b0 /
b1000 .
b1000 "
$end
#0
$dumpvars
b0 g
ze
0d
0c
xa
z^
0]
0\
xZ
zW
0V
0U
xS
zP
0O
0N
xL
zI
0H
0G
xE
zB
0A
0@
x>
z;
0:
09
x7
z4
03
02
x0
bz -
b0 ,
0+
bx *
bx )
1(
0'
0&
bx %
0$
b0 #
bz !
$end
#5000
1$
#10000
00
07
0>
1E
0L
0S
0Z
1a
0$
b10001000 %
b10001000 *
b10001000 #
b0 )
0(
#11000
04
0;
0B
0I
0P
0W
0^
b0 !
b0 -
0e
1+
1'
b11 g
1&
#15000
1I
b10001000 !
b10001000 -
1e
1H
1d
1G
b10001000 ,
1c
1$
#20000
z4
z;
zB
zI
zP
zW
z^
bz !
bz -
ze
0$
0'
0+
b0 g
0&
#25000
1$
#30000
0E
1L
1S
1Z
0$
b11110000 %
b11110000 *
b11110000 #
b1 )
#31000
04
0;
0B
1I
0P
0W
0^
b10001000 !
b10001000 -
1e
1+
1'
b11 g
1&
#35000
0I
1P
1W
b11110000 !
b11110000 -
1^
0H
1O
1V
1]
0G
1N
1U
b11110000 ,
1\
1$
#40000
z4
z;
zB
zI
zP
zW
z^
bz !
bz -
ze
0$
0'
0+
b0 g
0&
#45000
1$
#50000
10
1>
0S
0a
0$
b1010101 %
b1010101 *
b1010101 #
b10 )
#51000
04
0;
0B
0I
1P
1W
1^
b11110000 !
b11110000 -
1e
1+
1'
b11 g
1&
#55000
14
1B
0W
b1010101 !
b1010101 -
0e
13
1A
0V
0d
12
1@
0U
b1010101 ,
0c
1$
#60000
z4
z;
zB
zI
zP
zW
z^
bz !
bz -
ze
0$
0'
0+
b0 g
0&
#65000
1$
#70000
00
1E
0L
1a
0$
b11001100 %
b11001100 *
b11001100 #
b11 )
#71000
14
0;
1B
0I
1P
0W
1^
b1010101 !
b1010101 -
0e
1+
1'
b11 g
1&
#75000
04
1I
0P
b11001100 !
b11001100 -
1e
03
1H
0O
1d
02
1G
0N
b11001100 ,
1c
1$
#80000
z4
z;
zB
zI
zP
zW
z^
bz !
bz -
ze
0$
0'
0+
b0 g
0&
#85000
1$
#90000
0$
b100 )
