rtl/lib/decoder/decoder_n.v
`timescale 1ns/1ps

module decoder_n #(parameter WIDTH = 2) (input [WIDTH-1:0] in, output reg [2**WIDTH-1:0] y);

always @ (*) begin 
  y = 0; // Initialize the output to 0
  y[in] = 1; // Set the bit corresponding to the input value to 1, all other bits will be 0
end 
endmodule

rtl/lib/decoder/decoder_n_tb.v
module decoder_tb();
parameter N = 3; // Number of input bits for the decoder, which will determine the size of the output (2^N)
reg [N-1:0] tb_in;
wire [2**N-1:0] tb_y;

reg [10:0] testvectors [0:7]; // An array to hold our test vectors, each vector is 11 bits: {in[2:0], expected_y[7:0]}
reg [2**N-1:0] y_expected; // To hold the expected value of the output for each test case
integer i; // Our Page turner

decoder_n #(.WIDTH(N)) dut (.in(tb_in), .y(tb_y));

// Test all possible input combinations
initial begin 
  $dumpfile("sim/decoder/decoder.vcd");
  $dumpvars(0, decoder_tb);
  $readmemb("rtl/lib/decoder/decoder.tv", testvectors); // Load our test vectors from a file

  // Automation loop to apply test vectors
  for (i = 0; i < 8; i= i + 1) begin 
    {tb_in, y_expected} = testvectors[i]; // Split the 11-bit testvector into input and expected output
    #10; // Wait for the output to stabilize after applying inputs

    if (tb_y !== y_expected) begin 
      $display("Test Case %d failed: Input = %b, Expected Output = %b, Actual Output = %b", i, tb_in, y_expected, tb_y);
    end else begin 
      $display("Test Case %d passed: Input = %b, Output = %b", i, tb_in, tb_y);
    end
  end
  $display("All test cases completed");
  $finish;
end
endmodule

sim/decoder/decoder.vcd
$date
	Wed May 13 13:07:50 2026
$end
$version
	Icarus Verilog
$end
$timescale
	1s
$end
$scope module decoder_tb $end
$var wire 8 ! tb_y [7:0] $end
$var parameter 32 " N $end
$var reg 3 # tb_in [2:0] $end
$var reg 8 $ y_expected [7:0] $end
$var integer 32 % i [31:0] $end
$scope module dut $end
$var wire 3 & in [2:0] $end
$var parameter 32 ' WIDTH $end
$var reg 8 ( y [7:0] $end
$upscope $end
$upscope $end
$enddefinitions $end
$comment Show the parameter values. $end
$dumpall
b11 '
b11 "
$end
#0
$dumpvars
b1 (
b0 &
b0 %
b1 $
b0 #
b1 !
$end
#10
b10 !
b10 (
b1 #
b1 &
b10 $
b1 %
#20
b100 !
b100 (
b10 #
b10 &
b100 $
b10 %
#30
b1000 !
b1000 (
b11 #
b11 &
b1000 $
b11 %
#40
b10000 !
b10000 (
b100 #
b100 &
b10000 $
b100 %
#50
b100000 !
b100000 (
b101 #
b101 &
b100000 $
b101 %
#60
b1000000 !
b1000000 (
b110 #
b110 &
b1000000 $
b110 %
#70
b10000000 !
b10000000 (
b111 #
b111 &
b10000000 $
b111 %
#80
b1000 %
