rtl/lib/en_dff/en_dff.v
`timescale 1ns/1ps

module en_dff #(parameter WIDTH = 1) (input en, input clk, input reset, input [WIDTH-1:0] d, output reg q);

always @ (posedge clk, posedge reset) 
  if (en) begin 
   q <= d;
  end else if (reset) begin 
    q <= 0;
  end
  
endmodule

rtl/submodules/ram_address_selector/ras.v
`timescale 1ns/1ps

module ras #(parameter WIDTH = 4) (
  input clk, 
  input reset_sig,
  input [WIDTH-1:0] addr,  
  input en_ras, 
  output [WIDTH-1:0] ras_q);
 
 genvar i; // Declare a generate variable for use in the generate block to create multiple instances of the enable D flip-flop for each bit of the RAM address selector register.
 generate 
   for (i = 0; i < WIDTH; i = i + 1) begin: en_dff 
       
       en_dff #(.WIDTH(1)) dff (.en(en_ras), .clk(clk),.d(addr[i]), .reset(reset_sig), .q(ras_q[i])); // Use an enable D flip-flop for each bit of the RAM address selector register. The flip-flop will only update its output (ras_q[i]) with the input data (addr[i]) when the en_ras signal is high, allowing for controlled loading of the RAM address into the register. This design allows the RAM address selector to hold its value when not enabled, which can be useful for maintaining a stable address for RAM access in a larger system.
   end
 endgenerate
  
endmodule

rtl/submodules/ram_address_selector/ras_tb.v
`timescale 1ns/1ps

module ras_tb();
parameter W = 4;

reg [W-1:0] tb_addr;
reg tb_clk;
reg tb_reset;
reg tb_en_ras;
wire [W-1:0] tb_ras_q;

reg [7:0] test_vectors [0:4];
reg [W-1:0] expected_q;

ras #(.WIDTH(W)) dut (
  .addr(tb_addr), 
  .clk(tb_clk), 
  .reset_sig(tb_reset), 
  .en_ras(tb_en_ras), 
  .ras_q(tb_ras_q)
);

initial tb_clk = 0; // Initialize the clock signal to 0
always #5 tb_clk = ~tb_clk; // Generate a clock signal with a period of 10 time units
integer i; // Declare an integer variable for use as a loop counter in the testbench

initial begin 
  $dumpfile("sim/ram_address_selector/ras.vcd");
  $dumpvars(0, ras_tb);
  $readmemb("rtl/submodules/ram_address_selector/ras.tv", test_vectors); // Load test data from a memory file into the test_vectors array

   i = 0; // Initialize the loop counter to 0
   tb_en_ras = 0; // Initialize the enable signal to 0
   tb_addr = {W{1'b0}}; // Initialize the address input to 0
   expected_q = {W{1'b0}}; // Initialize the expected output to 0
   tb_reset = 1; // Assert the reset signal to initialize the RAM address selector register
    #10; // Wait for 10 time units to allow the DUT to process the reset signal
   tb_reset = 0;
   #5; // Wait for 5 time units to ensure the reset signal is deasserted before starting the test

   for (i = 0; i < 5; i = i + 1) begin 
    {tb_addr, expected_q} = test_vectors[i]; // Assign the test vector values to the input signals and expected output

     tb_en_ras = 1; // Assert the enable signal to load the address into the RAM address selector register
     #1;
    @ (posedge tb_clk); // Wait for the positive edge of the clock to ensure that the inputs are registered in the RAM address selector before checking the output
  
    if (tb_ras_q !== expected_q) $display("Test failed for input %b: expected %b, got %b", tb_addr, expected_q, tb_ras_q); // Check if the output matches the expected value and display an error message if it does not.
    else $display("Test passed for input %b: expected %b, got %b", tb_addr, expected_q, tb_ras_q); // Display a success message if the output matches the expected value.
     
     tb_en_ras = 0;
     #10; // Wait for 10 time units to allow the DUT to process the change in the enable signal and test that the RAM address selector register holds its value when not enabled
      if (tb_ras_q !== expected_q) $display("Hold test failed for input %b: expected %b, got %b", tb_addr, expected_q, tb_ras_q); // Check if the output matches the expected value and display an error message if it does not.
   end
    $display("All tests completed"); // Display a message indicating that all tests have been completed
    $finish; // Terminate the simulation
end
endmodule

sim/ram_address_selector/ras.vcd
$date
	Fri May 22 14:08:11 2026
$end
$version
	Icarus Verilog
$end
$timescale
	1s
$end
$scope module ras_tb $end
$var wire 4 ! tb_ras_q [3:0] $end
$var parameter 32 " W $end
$var reg 4 # expected_q [3:0] $end
$var reg 4 $ tb_addr [3:0] $end
$var reg 1 % tb_clk $end
$var reg 1 & tb_en_ras $end
$var reg 1 ' tb_reset $end
$var integer 32 ( i [31:0] $end
$scope module dut $end
$var wire 4 ) addr [3:0] $end
$var wire 1 % clk $end
$var wire 1 & en_ras $end
$var wire 1 ' reset_sig $end
$var wire 4 * ras_q [3:0] $end
$var parameter 32 + WIDTH $end
$scope begin en_dff[0] $end
$var parameter 2 , i $end
$scope module dff $end
$var wire 1 % clk $end
$var wire 1 - d $end
$var wire 1 & en $end
$var wire 1 ' reset $end
$var parameter 32 . WIDTH $end
$var reg 1 / q $end
$upscope $end
$upscope $end
$scope begin en_dff[1] $end
$var parameter 2 0 i $end
$scope module dff $end
$var wire 1 % clk $end
$var wire 1 1 d $end
$var wire 1 & en $end
$var wire 1 ' reset $end
$var parameter 32 2 WIDTH $end
$var reg 1 3 q $end
$upscope $end
$upscope $end
$scope begin en_dff[2] $end
$var parameter 3 4 i $end
$scope module dff $end
$var wire 1 % clk $end
$var wire 1 5 d $end
$var wire 1 & en $end
$var wire 1 ' reset $end
$var parameter 32 6 WIDTH $end
$var reg 1 7 q $end
$upscope $end
$upscope $end
$scope begin en_dff[3] $end
$var parameter 3 8 i $end
$scope module dff $end
$var wire 1 % clk $end
$var wire 1 9 d $end
$var wire 1 & en $end
$var wire 1 ' reset $end
$var parameter 32 : WIDTH $end
$var reg 1 ; q $end
$upscope $end
$upscope $end
$upscope $end
$upscope $end
$enddefinitions $end
$comment Show the parameter values. $end
$dumpall
b1 :
b11 8
b1 6
b10 4
b1 2
b1 0
b1 .
b0 ,
b100 +
b100 "
$end
#0
$dumpvars
0;
09
07
05
03
01
0/
0-
b0 *
b0 )
b0 (
1'
0&
0%
b0 $
b0 #
b0 !
$end
#5
1%
#10
0%
0'
#15
1%
1&
#20
0%
#25
0&
1%
#30
0%
#35
1/
13
17
b1111 !
b1111 *
1;
1-
11
15
19
1%
1&
b1111 $
b1111 )
b1111 #
b1 (
#40
0%
#45
0&
1%
#50
0%
#55
0/
b1010 !
b1010 *
07
0-
05
1%
1&
b1010 $
b1010 )
b1010 #
b10 (
#60
0%
#65
0&
1%
#70
0%
#75
1/
03
17
b101 !
b101 *
0;
1-
01
15
09
1%
1&
b101 $
b101 )
b101 #
b11 (
#80
0%
#85
0&
1%
#90
0%
#95
0/
13
b1110 !
b1110 *
1;
0-
11
19
1%
1&
b1110 $
b1110 )
b1110 #
b100 (
#100
0%
#105
0&
1%
#110
0%
#115
1%
b101 (
