rtl/lib/tristate_buff_n/tristate_buff_n.v
`timescale 1ns/1ps

module tristate_buff_n #(parameter WIDTH = 1) (input en, input [WIDTH-1:0] a, output [WIDTH-1:0] y);
assign y = en ? a :{WIDTH{1'bz}};
endmodule

rtl/lib/en_dff/en_dff.v
module en_dff #(parameter WIDTH = 1) (input en, input clk, input reset, input [WIDTH-1:0] d, output reg q);

always @ (posedge clk, posedge reset) 
  if (en) begin 
   q <= d;
  end else if (reset) begin 
    q <= 0;
  end
  
endmodule

rtl/submodules/instruction_register/instruction_register.v
module instruction_register #(parameter WIDTH = 8) (input clk, input en_load, input reset_sig, input [WIDTH-1:0] instr_d, output [WIDTH-1:0] instruction_q);

 genvar i; // Declare a generate variable for use in the generate block to create multiple instances of the enable D flip-flop for each bit of the instruction register.
 generate 
  for (i = 0; i < WIDTH; i = i + 1) begin: en_dff 

   en_dff #(.WIDTH(1)) dff (.clk(clk), .en(en_load), .reset(reset_sig), .d(instr_d[i]), .q(instruction_q[i])); // Use an enable D flip-flop for each bit of the instruction register. The flip-flop will only update its output (q[i]) with the input data (d[i]) when the en_load signal is high, allowing for controlled loading of instructions into the register. The reset_sig can be used to asynchronously reset the register to a known state (e.g., all zeros) when needed.

  end
 endgenerate
endmodule

rtl/subsystems_tests/decode_phase/decode_phase.v
module decode_phase #(parameter WORD_WIDTH = 8) (
  input clk, 
  input reset,
  input dec_en_ir_in,
  input dec_en_ir_out,
  input [WORD_WIDTH-1:0] dec_instr_d,

  output [WORD_WIDTH-1:0] dec_out_view_bus
);
 
 wire [WORD_WIDTH-1:0] w_bus; // Internal bus to connect the outputs of the decode phase to the next stage (e.g., execute phase) and for testing purposes.

 assign dec_out_view_bus = w_bus; // Connect the internal bus to an output for testing and  observation purposes.

 wire [WORD_WIDTH-1:0] ir_out; // Output of the instruction register, which holds the currently decoded instruction.

 // Instantiating Instruction Register
instruction_register #(.WIDTH(WORD_WIDTH)) instruction_register_inst (
  .clk(clk), 
  .en_load(dec_en_ir_in), 
  .reset_sig(reset), 
  .instr_d(dec_instr_d), 

  .instruction_q(ir_out)
  );

// Tristate Buffer connecting IR output to the W-Bus
tristate_buff_n #(.WIDTH(4)) ir_bus_driver (.a(ir_out[3:0]), .en(dec_en_ir_out), .y(w_bus[3:0]));

endmodule

rtl/subsystems_tests/decode_phase/decode_phase_tb.v
module decode_phase_tb();
parameter WORD_W = 8;

reg tb_clk;
reg tb_reset;
reg tb_dec_en_ir_in;
reg tb_dec_en_ir_out;
reg [WORD_W-1:0] tb_dec_instr_d; // This is the input instruction to be loaded into the instruction register for decoding. It should be set according to the test vectors to verify the correct decoding behavior of the decode phase.
reg [17:0] test_vectors [0:5];
reg [WORD_W-1:0] expected_dec_out_view_bus;

wire [WORD_W-1:0] tb_dec_out_view_bus;

decode_phase #(.WORD_WIDTH(WORD_W)) decode_phase_inst (
  .clk(tb_clk), 
  .reset(tb_reset), 
  .dec_instr_d(tb_dec_instr_d),
  .dec_en_ir_in(tb_dec_en_ir_in), 
  .dec_en_ir_out(tb_dec_en_ir_out), 
  .dec_out_view_bus(tb_dec_out_view_bus)
);

initial tb_clk = 0;
always #5 tb_clk = ~tb_clk; // 10 time units clock period

integer vector_index = 0;
initial begin
  $dumpfile("sim/decode_phase/decode_phase.vcd");
  $dumpvars(0, decode_phase_tb);
  $readmemb("rtl/subsystems_tests/decode_phase/decode_phase.tv", test_vectors);

  // Initialize inputs
  tb_reset = 1; // Start in reset
  tb_dec_en_ir_in = 0;
  tb_dec_en_ir_out = 0;

  #15;          // Hold reset for more than one clock cycle
  tb_reset = 0; // Release reset
  #10;

  while (test_vectors[vector_index] !== 18'bx) begin
    @ (negedge tb_clk); // Wait for the negative edge of the clock to ensure that the inputs are registered in the decode phase before checking the output
    {
      tb_dec_en_ir_in, 
      tb_dec_en_ir_out, 
      tb_dec_instr_d,
       expected_dec_out_view_bus
     } = test_vectors[vector_index];
    {
      tb_dec_en_ir_in, 
      tb_dec_en_ir_out, 
      tb_dec_instr_d,
      expected_dec_out_view_bus
     } = test_vectors[vector_index];

     #2; // Wait for a short time to let the values propagate through the system before checking the output
    if (tb_dec_out_view_bus !== expected_dec_out_view_bus) begin
      $display("Test Vector %0d Failed: Expected dec_out_view_bus = %b, Actual dec_out_view_bus = %b", vector_index, expected_dec_out_view_bus, tb_dec_out_view_bus);
    end else begin
      $display("Test Vector %0d Passed: dec_out_view_bus = %b", vector_index, tb_dec_out_view_bus);
    end

    vector_index = vector_index + 1;
   end
  $display("All Test cases completed.");
  $finish;
 end
 
endmodule

sim/decode_phase/decode_phase.vcd
$date
	Sun May 24 20:57:27 2026
$end
$version
	Icarus Verilog
$end
$timescale
	1ps
$end
$scope module decode_phase_tb $end
$var wire 8 ! tb_dec_out_view_bus [7:0] $end
$var parameter 32 " WORD_W $end
$var reg 8 # expected_dec_out_view_bus [7:0] $end
$var reg 1 $ tb_clk $end
$var reg 1 % tb_dec_en_ir_in $end
$var reg 1 & tb_dec_en_ir_out $end
$var reg 8 ' tb_dec_instr_d [7:0] $end
$var reg 1 ( tb_reset $end
$var integer 32 ) vector_index [31:0] $end
$scope module decode_phase_inst $end
$var wire 1 $ clk $end
$var wire 1 % dec_en_ir_in $end
$var wire 1 & dec_en_ir_out $end
$var wire 8 * dec_instr_d [7:0] $end
$var wire 8 + dec_out_view_bus [7:0] $end
$var wire 1 ( reset $end
$var wire 8 , w_bus [7:0] $end
$var wire 8 - ir_out [7:0] $end
$var parameter 32 . WORD_WIDTH $end
$scope module instruction_register_inst $end
$var wire 1 $ clk $end
$var wire 1 % en_load $end
$var wire 8 / instr_d [7:0] $end
$var wire 1 ( reset_sig $end
$var wire 8 0 instruction_q [7:0] $end
$var parameter 32 1 WIDTH $end
$scope begin en_dff[0] $end
$var parameter 2 2 i $end
$scope module dff $end
$var wire 1 $ clk $end
$var wire 1 3 d $end
$var wire 1 % en $end
$var wire 1 ( reset $end
$var parameter 32 4 WIDTH $end
$var reg 1 5 q $end
$upscope $end
$upscope $end
$scope begin en_dff[1] $end
$var parameter 2 6 i $end
$scope module dff $end
$var wire 1 $ clk $end
$var wire 1 7 d $end
$var wire 1 % en $end
$var wire 1 ( reset $end
$var parameter 32 8 WIDTH $end
$var reg 1 9 q $end
$upscope $end
$upscope $end
$scope begin en_dff[2] $end
$var parameter 3 : i $end
$scope module dff $end
$var wire 1 $ clk $end
$var wire 1 ; d $end
$var wire 1 % en $end
$var wire 1 ( reset $end
$var parameter 32 < WIDTH $end
$var reg 1 = q $end
$upscope $end
$upscope $end
$scope begin en_dff[3] $end
$var parameter 3 > i $end
$scope module dff $end
$var wire 1 $ clk $end
$var wire 1 ? d $end
$var wire 1 % en $end
$var wire 1 ( reset $end
$var parameter 32 @ WIDTH $end
$var reg 1 A q $end
$upscope $end
$upscope $end
$scope begin en_dff[4] $end
$var parameter 4 B i $end
$scope module dff $end
$var wire 1 $ clk $end
$var wire 1 C d $end
$var wire 1 % en $end
$var wire 1 ( reset $end
$var parameter 32 D WIDTH $end
$var reg 1 E q $end
$upscope $end
$upscope $end
$scope begin en_dff[5] $end
$var parameter 4 F i $end
$scope module dff $end
$var wire 1 $ clk $end
$var wire 1 G d $end
$var wire 1 % en $end
$var wire 1 ( reset $end
$var parameter 32 H WIDTH $end
$var reg 1 I q $end
$upscope $end
$upscope $end
$scope begin en_dff[6] $end
$var parameter 4 J i $end
$scope module dff $end
$var wire 1 $ clk $end
$var wire 1 K d $end
$var wire 1 % en $end
$var wire 1 ( reset $end
$var parameter 32 L WIDTH $end
$var reg 1 M q $end
$upscope $end
$upscope $end
$scope begin en_dff[7] $end
$var parameter 4 N i $end
$scope module dff $end
$var wire 1 $ clk $end
$var wire 1 O d $end
$var wire 1 % en $end
$var wire 1 ( reset $end
$var parameter 32 P WIDTH $end
$var reg 1 Q q $end
$upscope $end
$upscope $end
$upscope $end
$scope module ir_bus_driver $end
$var wire 4 R a [3:0] $end
$var wire 1 & en $end
$var wire 4 S y [3:0] $end
$var parameter 32 T WIDTH $end
$upscope $end
$upscope $end
$upscope $end
$enddefinitions $end
$comment Show the parameter values. $end
$dumpall
b100 T
b1 P
b111 N
b1 L
b110 J
b1 H
b101 F
b1 D
b100 B
b1 @
b11 >
b1 <
b10 :
b1 8
b1 6
b1 4
b0 2
b1000 1
b1000 .
b1000 "
$end
#0
$dumpvars
bz S
b0 R
0Q
xO
0M
xK
0I
xG
0E
xC
0A
x?
0=
x;
09
x7
05
x3
b0 0
bx /
b0 -
bz ,
bz +
bx *
b0 )
1(
bx '
0&
0%
0$
bx #
bz !
$end
#5000
1$
#10000
0$
#15000
1$
0(
#20000
0$
#25000
1$
#30000
13
07
1;
0?
1C
0G
1K
0O
1%
b1010101 '
b1010101 *
b1010101 /
bz #
0$
#32000
b1 )
#35000
b101 R
15
1=
1E
b1010101 -
b1010101 0
1M
1$
#40000
bz0101 !
bz0101 +
bz0101 ,
b101 S
0%
1&
bz0101 #
0$
#42000
b10 )
#45000
1$
#50000
bz !
bz +
bz ,
bz S
03
0;
1G
1O
1%
0&
b11110000 '
b11110000 *
b11110000 /
bz #
0$
#52000
b11 )
#55000
b0 R
05
0=
1I
b11110000 -
b11110000 0
1Q
1$
#60000
bz0000 !
bz0000 +
bz0000 ,
b0 S
0%
1&
bz0000 #
0$
#62000
b100 )
#65000
1$
#70000
bz !
bz +
bz ,
bz S
13
0G
0K
0O
1%
0&
b10001 '
b10001 *
b10001 /
bz #
0$
#72000
b101 )
#75000
b1 R
15
0I
0M
b10001 -
b10001 0
0Q
1$
#80000
bz0001 !
bz0001 +
bz0001 ,
b1 S
0%
1&
bz0001 #
0$
#82000
b110 )
