rtl/lib/en_dff/en_dff.v
`timescale 1ns/1ps

module en_dff #(parameter WIDTH = 1) (input en, input clk, input reset, input [WIDTH-1:0] d, output reg q);

always @ (posedge clk, posedge reset) 
  if (en) begin 
   q <= d;
  end else if (reset) begin 
    q <= 0;
  end
  
endmodule

rtl/submodules/instruction_register/instruction_register.v
`timescale 1ns/1ps

module instruction_register #(parameter WIDTH = 8) (input clk, input en_load, input reset_sig, input [WIDTH-1:0] instr_d, output [WIDTH-1:0] instruction_q);

 genvar i; // Declare a generate variable for use in the generate block to create multiple instances of the enable D flip-flop for each bit of the instruction register.
 generate 
  for (i = 0; i < WIDTH; i = i + 1) begin: en_dff 

   en_dff #(.WIDTH(1)) dff (.clk(clk), .en(en_load), .reset(reset_sig), .d(instr_d[i]), .q(instruction_q[i])); // Use an enable D flip-flop for each bit of the instruction register. The flip-flop will only update its output (q[i]) with the input data (d[i]) when the en_load signal is high, allowing for controlled loading of instructions into the register. The reset_sig can be used to asynchronously reset the register to a known state (e.g., all zeros) when needed.
   
  end
 endgenerate
endmodule

rtl/submodules/instruction_register/instruction_register_tb.v
`timescale 1ns/1ps

module instruction_register_tb();
parameter W = 8;

reg [W-1:0] tb_d;
wire [W-1:0] tb_q;
reg tb_en_load;
reg tb_reset;
reg tb_clk;
reg [15:0] test_vectors [0:5];
reg [W-1:0] expected_d;
reg [W-1:0] expected_q;

initial tb_clk = 0; // Initialize the clock signal to 0
always #5 tb_clk = ~tb_clk; // Generate a clock signal with a period of 10 time units

instruction_register #(.WIDTH(W)) dut (
  .clk(tb_clk), 
  .en_load(tb_en_load), 
  .reset_sig(tb_reset), 
  .instr_d(tb_d), 
  .instruction_q(tb_q)
);

integer i; // Declare an integer variable for use as a loop counter in the testbench
initial begin 
  $dumpfile("sim/instruction_register/instruction_register.vcd");
  $dumpvars(0, instruction_register_tb);
  $readmemb("rtl/submodules/instruction_register/instruction_register.tv", test_vectors); // Load test data from a memory file into the test_vectors array

   i = 0; // Initialize the loop counter to 0
   tb_en_load  = 0; // Initialize the enable load signal to 0
   tb_d = {W{1'b0}}; // Initialize the data input to 0
   expected_q = {W{1'b0}}; // Initialize the expected output to 0
   tb_reset = 1; // Assert the reset signal to initialize the instruction register
    #10; // Wait for 10 time units to allow the DUT to process the reset signal
   tb_reset = 0;
   #5; // Wait for 5 time units to ensure the reset signal is deasserted before starting the test

 for (i = 0; i < 6; i = i+ 1) begin 
  {tb_d, expected_q} = test_vectors[i]; // Assign the test vector values to the input signals and expected output
    tb_en_load = 1; // Assert the enable load signal to load the instruction into the register
    #1; // Wait for 1 time units to allow the DUT to process the input data and load it into the register
    @ (posedge tb_clk); // Wait for the positive edge of the clock to ensure that the instruction is loaded into the register before checking the output

   if (tb_q !== expected_q) $display("Test failed for input %b: expected %b, got %b", tb_d, expected_q, tb_q); // Check if the output matches the expected value and display an error message if it does not.
   else $display("Test passed for input %b: expected %b, got %b", tb_d, expected_q, tb_q); // Display a success message if the output matches the expected value.
    
   tb_en_load = 0; // Deassert the enable load signal to test that the instruction register holds its value when not enabled
    #10; // Wait for 10 time units to allow the DUT to process the change in the enable signal
 end
   $display("All tests completed"); // Display a message indicating that all tests have been completed
   $finish; // Terminate the simulation
end
endmodule

sim/instruction_register/instruction_register.vcd
$date
	Fri May 22 12:43:00 2026
$end
$version
	Icarus Verilog
$end
$timescale
	1s
$end
$scope module instruction_register_tb $end
$var wire 8 ! tb_q [7:0] $end
$var parameter 32 " W $end
$var reg 8 # expected_q [7:0] $end
$var reg 1 $ tb_clk $end
$var reg 8 % tb_d [7:0] $end
$var reg 1 & tb_en_load $end
$var reg 1 ' tb_reset $end
$var integer 32 ( i [31:0] $end
$scope module dut $end
$var wire 1 $ clk $end
$var wire 1 & en_load $end
$var wire 8 ) instr_d [7:0] $end
$var wire 1 ' reset_sig $end
$var wire 8 * instruction_q [7:0] $end
$var parameter 32 + WIDTH $end
$scope begin en_dff[0] $end
$var parameter 2 , i $end
$scope module dff $end
$var wire 1 $ clk $end
$var wire 1 - d $end
$var wire 1 & en $end
$var wire 1 ' reset $end
$var parameter 32 . WIDTH $end
$var reg 1 / q $end
$upscope $end
$upscope $end
$scope begin en_dff[1] $end
$var parameter 2 0 i $end
$scope module dff $end
$var wire 1 $ clk $end
$var wire 1 1 d $end
$var wire 1 & en $end
$var wire 1 ' reset $end
$var parameter 32 2 WIDTH $end
$var reg 1 3 q $end
$upscope $end
$upscope $end
$scope begin en_dff[2] $end
$var parameter 3 4 i $end
$scope module dff $end
$var wire 1 $ clk $end
$var wire 1 5 d $end
$var wire 1 & en $end
$var wire 1 ' reset $end
$var parameter 32 6 WIDTH $end
$var reg 1 7 q $end
$upscope $end
$upscope $end
$scope begin en_dff[3] $end
$var parameter 3 8 i $end
$scope module dff $end
$var wire 1 $ clk $end
$var wire 1 9 d $end
$var wire 1 & en $end
$var wire 1 ' reset $end
$var parameter 32 : WIDTH $end
$var reg 1 ; q $end
$upscope $end
$upscope $end
$scope begin en_dff[4] $end
$var parameter 4 < i $end
$scope module dff $end
$var wire 1 $ clk $end
$var wire 1 = d $end
$var wire 1 & en $end
$var wire 1 ' reset $end
$var parameter 32 > WIDTH $end
$var reg 1 ? q $end
$upscope $end
$upscope $end
$scope begin en_dff[5] $end
$var parameter 4 @ i $end
$scope module dff $end
$var wire 1 $ clk $end
$var wire 1 A d $end
$var wire 1 & en $end
$var wire 1 ' reset $end
$var parameter 32 B WIDTH $end
$var reg 1 C q $end
$upscope $end
$upscope $end
$scope begin en_dff[6] $end
$var parameter 4 D i $end
$scope module dff $end
$var wire 1 $ clk $end
$var wire 1 E d $end
$var wire 1 & en $end
$var wire 1 ' reset $end
$var parameter 32 F WIDTH $end
$var reg 1 G q $end
$upscope $end
$upscope $end
$scope begin en_dff[7] $end
$var parameter 4 H i $end
$scope module dff $end
$var wire 1 $ clk $end
$var wire 1 I d $end
$var wire 1 & en $end
$var wire 1 ' reset $end
$var parameter 32 J WIDTH $end
$var reg 1 K q $end
$upscope $end
$upscope $end
$upscope $end
$upscope $end
$enddefinitions $end
$comment Show the parameter values. $end
$dumpall
b1 J
b111 H
b1 F
b110 D
b1 B
b101 @
b1 >
b100 <
b1 :
b11 8
b1 6
b10 4
b1 2
b1 0
b1 .
b0 ,
b1000 +
b1000 "
$end
#0
$dumpvars
0K
0I
0G
0E
0C
0A
0?
0=
0;
09
07
05
03
01
0/
0-
b0 *
b0 )
b0 (
1'
0&
b0 %
0$
b0 #
b0 !
$end
#5
1$
#10
0$
0'
#15
1$
1&
#20
0$
#25
0&
1$
#30
0$
#35
1/
17
1?
b1010101 !
b1010101 *
1G
1-
15
1=
1E
1$
1&
b1010101 %
b1010101 )
b1010101 #
b1 (
#40
0$
#45
0&
1$
#50
0$
#55
13
1;
1C
b11111111 !
b11111111 *
1K
11
19
1A
1I
1$
1&
b11111111 %
b11111111 )
b11111111 #
b10 (
#60
0$
#65
0&
1$
#70
0$
#75
0/
03
07
0;
0?
0C
0G
b0 !
b0 *
0K
0-
01
05
09
0=
0A
0E
0I
1$
1&
b0 %
b0 )
b0 #
b11 (
#80
0$
#85
0&
1$
#90
0$
#95
1/
17
1?
b1010101 !
b1010101 *
1G
1-
15
1=
1E
1$
1&
b1010101 %
b1010101 )
b1010101 #
b100 (
#100
0$
#105
0&
1$
#110
0$
#115
13
1;
1C
b11111111 !
b11111111 *
1K
11
19
1A
1I
1$
1&
b11111111 %
b11111111 )
b11111111 #
b101 (
#120
0$
#125
0&
1$
#130
0$
#135
1$
b110 (
