rtl/lib/mux/mux.v
`timescale 1ns/1ps

module mux #(parameter WIDTH = 1) (input [WIDTH-1:0] d1, d0, input sel, output [WIDTH-1:0] y);
assign y = sel ? d1 : d0; // the output y is assigned the value of d1 if sel is 1, and the value of d0 if sel is 0. This is the behavior of a multiplexer, which selects one of the two inputs based on the value of sel.
endmodule

rtl/lib/full_adder/full_adder.v
`timescale 1ns/1ps

module full_adder (input a, b, cin, output reg sum, cout);
reg p, g;

always @ (*) begin 
 p = a ^ b;
 g  = a & b;
 sum = p ^ cin;
 cout  = g | (p & cin);
end

endmodule

rtl/lib/en_dff/en_dff.v
`timescale 1ns/1ps

module en_dff #(parameter WIDTH = 1) (input en, input clk, input reset, input [WIDTH-1:0] d, output reg q);

always @ (posedge clk, posedge reset) 
  if (en) begin 
   q <= d;
  end else if (reset) begin 
    q <= 0;
  end
  
endmodule

rtl/submodules/pc/pc.v
`timescale 1ns/1ps

module pc #(parameter WIDTH = 4) (
  input clk, 
  input  reset_sig,
  input [WIDTH-1:0] a, 
  input [WIDTH-1:0] b,  
  input add_sub, 
  input en_pc_in, 
  input en_pc_reg, 
  output [WIDTH-1:0] pc_q);

wire [WIDTH-1:0] internal_result;
wire [WIDTH-1:0] internal_a;
wire [WIDTH-1:0] internal_b;
wire [WIDTH-1:0] internal_sum;
wire [WIDTH-1:0] next_result;
wire [WIDTH:0] carry;
assign carry[0] = add_sub; // carry[0] is assigned the value of add_sub, which is the input signal that determines whether the operation is addition or subtraction. This is because in a full adder, the carry-in (cin) for the least significant bit (LSB) is determined by whether we are performing addition (carry-in = 0) or subtraction (carry-in = 1).

assign pc_q = internal_result; // The output of the program counter (PC) is assigned the value of internal_result, which is the registered value that holds the current state of the PC. This allows other parts of the system to read the current value of the PC for use in instruction fetching or other operations that require knowledge of the current program address.

genvar i;
generate 
for (i = 0; i < WIDTH; i = i + 1) begin: gen 

 assign internal_a[i] = a[i];
 assign internal_b[i] = b[i];

 // Register for the program counter (PC)
 en_dff #(.WIDTH(1)) pc_reg (.clk(clk), .en(en_pc_reg), .reset(reset_sig), .d(next_result[i]), .q(internal_result[i]));

 // Full adder to add A and B.
 full_adder fa (
  .a(internal_result[i]),
  .b(internal_b[i]),
  .cin(carry[i]),
  .sum(internal_sum[i]),
  .cout(carry[i + 1])
 );

 // MUX for selecting whether the input comes from BUS or the incremented sum from the adder.
 mux #(.WIDTH(1)) mux_inst (.d1(internal_a[i]), .d0(internal_sum[i]), .sel(en_pc_in), .y(next_result[i]));
   
end
endgenerate
  
endmodule

rtl/submodules/pc/pc_tb.v
`timescale 1ns/1ps

module pc_tb();
parameter W = 4;

// hardcoded b to 1
parameter [0:0] b0 = 1'b1;
parameter [0:0] b1 = 1'b0;
parameter [0:0] b2 = 1'b0;
parameter [0:0] b3 = 1'b0;

reg [W-1:0] tb_a;
reg tb_clk, tb_reset, tb_add_sub, tb_en_pc_in, tb_en_pc_reg;
wire [W-1:0] tb_pc_q;

reg [8:0] test_vectors [0:3];
reg [W-1:0] expected_q;

initial tb_clk = 0;
always #5 tb_clk = ~tb_clk;

pc #(.WIDTH(W)) dut (
  .a(tb_a), 
  .b({b3, b2, b1, b0}), 
  .clk(tb_clk), 
  .reset_sig(tb_reset), 
  .add_sub(tb_add_sub), 
  .en_pc_in(tb_en_pc_in), 
  .en_pc_reg(tb_en_pc_reg), 
  .pc_q(tb_pc_q)
);

integer i;
initial begin 
  $dumpfile("sim/pc/pc.vcd");
  $dumpvars(0, pc_tb);
  $readmemb("rtl/submodules/pc/pc.tv", test_vectors);

   i = 0;
   tb_a = {W{1'b0}};
   expected_q ={W{1'b0}};
   tb_add_sub = 0;
   tb_en_pc_in = 0;
   tb_en_pc_reg = 0;
   tb_reset = 1;
   repeat (2) @ (posedge tb_clk);
   #1; tb_reset = 0;

   for (i = 0; i < 4; i = i + 1) begin 
       {tb_a, tb_en_pc_in, expected_q} = test_vectors[i];
          
        #1;
         tb_en_pc_reg = 1;

         @ (posedge tb_clk);
         #1;

         if (tb_pc_q !== expected_q) begin 
          $display("Test %0d failed: tb_a = %b Expected q = %b Actual q = %b", i, tb_a, expected_q, tb_pc_q);  
         end else begin
         $display("Test %0d passed: tb_a = %b Expected q = %b Actual q = %b", i, tb_a, expected_q, tb_pc_q);
         end

         tb_en_pc_reg = 0;
         @ (posedge tb_clk);
   end

  $display("All test completed");
  $finish;
end

endmodule

sim/pc/pc.vcd
$date
	Fri May 22 12:54:55 2026
$end
$version
	Icarus Verilog
$end
$timescale
	1ps
$end
$scope module pc_tb $end
$var wire 4 ! tb_pc_q [3:0] $end
$var parameter 32 " W $end
$var parameter 1 # b0 $end
$var parameter 1 $ b1 $end
$var parameter 1 % b2 $end
$var parameter 1 & b3 $end
$var reg 4 ' expected_q [3:0] $end
$var reg 4 ( tb_a [3:0] $end
$var reg 1 ) tb_add_sub $end
$var reg 1 * tb_clk $end
$var reg 1 + tb_en_pc_in $end
$var reg 1 , tb_en_pc_reg $end
$var reg 1 - tb_reset $end
$var integer 32 . i [31:0] $end
$scope module dut $end
$var wire 4 / a [3:0] $end
$var wire 1 ) add_sub $end
$var wire 4 0 b [3:0] $end
$var wire 1 * clk $end
$var wire 1 + en_pc_in $end
$var wire 1 , en_pc_reg $end
$var wire 4 1 pc_q [3:0] $end
$var wire 1 - reset_sig $end
$var wire 4 2 next_result [3:0] $end
$var wire 4 3 internal_sum [3:0] $end
$var wire 4 4 internal_result [3:0] $end
$var wire 4 5 internal_b [3:0] $end
$var wire 4 6 internal_a [3:0] $end
$var wire 5 7 carry [4:0] $end
$var parameter 32 8 WIDTH $end
$scope begin gen[0] $end
$var parameter 2 9 i $end
$scope module fa $end
$var wire 1 : a $end
$var wire 1 ; b $end
$var wire 1 < cin $end
$var reg 1 = cout $end
$var reg 1 > g $end
$var reg 1 ? p $end
$var reg 1 @ sum $end
$upscope $end
$scope module mux_inst $end
$var wire 1 A d0 $end
$var wire 1 B d1 $end
$var wire 1 + sel $end
$var wire 1 C y $end
$var parameter 32 D WIDTH $end
$upscope $end
$scope module pc_reg $end
$var wire 1 * clk $end
$var wire 1 E d $end
$var wire 1 , en $end
$var wire 1 - reset $end
$var parameter 32 F WIDTH $end
$var reg 1 G q $end
$upscope $end
$upscope $end
$scope begin gen[1] $end
$var parameter 2 H i $end
$scope module fa $end
$var wire 1 I a $end
$var wire 1 J b $end
$var wire 1 K cin $end
$var reg 1 L cout $end
$var reg 1 M g $end
$var reg 1 N p $end
$var reg 1 O sum $end
$upscope $end
$scope module mux_inst $end
$var wire 1 P d0 $end
$var wire 1 Q d1 $end
$var wire 1 + sel $end
$var wire 1 R y $end
$var parameter 32 S WIDTH $end
$upscope $end
$scope module pc_reg $end
$var wire 1 * clk $end
$var wire 1 T d $end
$var wire 1 , en $end
$var wire 1 - reset $end
$var parameter 32 U WIDTH $end
$var reg 1 V q $end
$upscope $end
$upscope $end
$scope begin gen[2] $end
$var parameter 3 W i $end
$scope module fa $end
$var wire 1 X a $end
$var wire 1 Y b $end
$var wire 1 Z cin $end
$var reg 1 [ cout $end
$var reg 1 \ g $end
$var reg 1 ] p $end
$var reg 1 ^ sum $end
$upscope $end
$scope module mux_inst $end
$var wire 1 _ d0 $end
$var wire 1 ` d1 $end
$var wire 1 + sel $end
$var wire 1 a y $end
$var parameter 32 b WIDTH $end
$upscope $end
$scope module pc_reg $end
$var wire 1 * clk $end
$var wire 1 c d $end
$var wire 1 , en $end
$var wire 1 - reset $end
$var parameter 32 d WIDTH $end
$var reg 1 e q $end
$upscope $end
$upscope $end
$scope begin gen[3] $end
$var parameter 3 f i $end
$scope module fa $end
$var wire 1 g a $end
$var wire 1 h b $end
$var wire 1 i cin $end
$var reg 1 j cout $end
$var reg 1 k g $end
$var reg 1 l p $end
$var reg 1 m sum $end
$upscope $end
$scope module mux_inst $end
$var wire 1 n d0 $end
$var wire 1 o d1 $end
$var wire 1 + sel $end
$var wire 1 p y $end
$var parameter 32 q WIDTH $end
$upscope $end
$scope module pc_reg $end
$var wire 1 * clk $end
$var wire 1 r d $end
$var wire 1 , en $end
$var wire 1 - reset $end
$var parameter 32 s WIDTH $end
$var reg 1 t q $end
$upscope $end
$upscope $end
$upscope $end
$upscope $end
$enddefinitions $end
$comment Show the parameter values. $end
$dumpall
b1 s
b1 q
b11 f
b1 d
b1 b
b10 W
b1 U
b1 S
b1 H
b1 F
b1 D
b0 9
b100 8
0&
0%
0$
1#
b100 "
$end
#0
$dumpvars
0t
0r
0p
0o
0n
0m
0l
0k
0j
0i
0h
0g
0e
0c
0a
0`
0_
0^
0]
0\
0[
0Z
0Y
0X
0V
0T
0R
0Q
0P
0O
0N
0M
0L
0K
0J
0I
0G
1E
1C
0B
1A
1@
1?
0>
0=
0<
1;
0:
b0 7
b0 6
b1 5
b0 4
b1 3
b1 2
b0 1
b1 0
b0 /
b0 .
1-
0,
0+
0*
0)
b0 (
b0 '
b0 !
$end
#5000
1*
#10000
0*
#15000
1*
#16000
b1 '
0-
#17000
1,
#20000
0*
#25000
1T
1R
1P
0E
1O
b10 2
0C
1K
0A
b10 7
1=
b10 3
0@
1>
0?
1:
b1 !
b1 1
b1 4
1G
1*
#26000
0,
#30000
0*
#35000
1B
b1 6
b1 (
b1 /
b10 '
b1 .
1*
#36000
1,
#40000
0*
#45000
0c
0a
0_
1T
1E
0^
1R
b11 2
1C
0Z
1P
0K
1A
0L
1O
1N
b0 7
0=
b11 3
1@
0>
1?
1I
0:
1V
b10 !
b10 1
b10 4
0G
1*
#46000
0,
#50000
0*
#55000
0E
1c
1r
0C
1a
1p
0B
1Q
1`
1o
1T
b1110 6
b1110 2
1R
b1110 (
b1110 /
1+
b1110 '
b10 .
1*
#56000
1,
#60000
0*
#65000
1n
1_
1m
1l
b1111 3
1^
1]
1g
1X
1t
b1110 !
b1110 1
b1110 4
1e
1*
#66000
0,
#70000
0*
#75000
1E
b1111 2
1C
0+
b1111 '
b11 .
1*
#76000
1,
#80000
0*
#85000
0r
0p
0n
0c
1j
0m
0a
1i
0_
0T
1[
0^
0R
1Z
0P
0E
1L
0O
b0 2
0C
1K
0A
b11110 7
1=
b0 3
0@
1>
0?
1:
b1111 !
b1111 1
b1111 4
1G
1*
#86000
0,
#90000
0*
#95000
b100 .
1*
