rtl/lib/full_adder/full_adder.v
module full_adder (input a, b, cin, output reg sum, cout);
reg p, g;

always @ (*) begin 
 p = a ^ b;
 g  = a & b;
 sum = p ^ cin;
 cout  = g | (p & cin);
end

endmodule

rtl/lib/full_adder/full_adder_tb.v
module full_adder_tb();
reg tb_a, tb_b, tb_cin;
wire tb_sum, tb_cout;

reg [4:0] testvectors [0:7]; // A array to hold our test vectors, each vector is 5 bits: {a, b, cin, expected_sum, expected_cout}
reg sum_expected, cout_expected; // To hold the expected values of sum and cout for each test case
integer i; // Our Page turner

full_adder dut (.a(tb_a), .b(tb_b), .cin(tb_cin), .sum(tb_sum), .cout(tb_cout));

initial begin 
  $dumpfile("sim/full_adder/full_adder.vcd");
  $dumpvars(0, full_adder_tb);
 
  $readmemb("rtl/lib/full_adder/full_adder.tv", testvectors); // Load our test vectors from a file

  // Automation loop to apply test vectors
  for (i = 0; i < 8; i = i + 1) begin 
    {tb_a, tb_b, tb_cin, sum_expected, cout_expected} = testvectors[i]; //Split the 5-bit testvector into inputs and expected outputs
    #10; // Wait for the outputs to stabilize after applying inputs

    if (tb_sum !== sum_expected || tb_cout !== cout_expected) begin 
      $display("Test Case %d failed", i);
    end else begin 
      $display("Test Case %d passed", i);
    end
    end
    $display("All test cases completed");
    $finish;
end

endmodule

sim/full_adder/full_adder.vcd
$date
	Sun May 10 15:46:18 2026
$end
$version
	Icarus Verilog
$end
$timescale
	1s
$end
$scope module full_adder_tb $end
$var wire 1 ! tb_sum $end
$var wire 1 " tb_cout $end
$var reg 1 # cout_expected $end
$var reg 1 $ sum_expected $end
$var reg 1 % tb_a $end
$var reg 1 & tb_b $end
$var reg 1 ' tb_cin $end
$var integer 32 ( i [31:0] $end
$scope module dut $end
$var wire 1 % a $end
$var wire 1 & b $end
$var wire 1 ' cin $end
$var reg 1 " cout $end
$var reg 1 ) g $end
$var reg 1 * p $end
$var reg 1 ! sum $end
$upscope $end
$upscope $end
$enddefinitions $end
$comment Show the parameter values. $end
$dumpall
$end
#0
$dumpvars
0*
0)
b0 (
0'
0&
0%
0$
0#
0"
0!
$end
#10
1!
1'
1$
b1 (
#20
1*
1&
0'
b10 (
#30
1"
0!
1'
0$
1#
b11 (
#40
0"
1!
1%
0&
0'
1$
0#
b100 (
#50
1"
0!
1'
0$
1#
b101 (
#60
1)
0*
1&
0'
b110 (
#70
1!
1'
1$
b111 (
#80
b1000 (
